yoyodyne_pretrained/__init__.py
yoyodyne_pretrained/callbacks.py
yoyodyne_pretrained/cli.py
yoyodyne_pretrained/defaults.py
yoyodyne_pretrained/metrics.py
yoyodyne_pretrained/models.py
yoyodyne_pretrained/data/__init__.py
yoyodyne_pretrained/data/batches.py
yoyodyne_pretrained/data/collators.py
yoyodyne_pretrained/data/datamodules.py
yoyodyne_pretrained/data/datasets.py
yoyodyne_pretrained/data/tsv.py
yoyodyne_pretrained-0.1.8.dist-info/licenses/LICENSE.txt
yoyodyne_pretrained-0.1.8.dist-info/METADATA
yoyodyne_pretrained-0.1.8.dist-info/WHEEL
yoyodyne_pretrained-0.1.8.dist-info/entry_points.txt
yoyodyne_pretrained-0.1.8.dist-info/top_level.txt
yoyodyne_pretrained-0.1.8.dist-info/RECORD
