Metadata-Version: 2.4
Name: yoyodyne-pretrained
Version: 0.1.8
Summary: Small-vocabulary transformer sequence-to-sequence models with warm starts
Author-email: Kyle Gorman <kylebgorman@gmail.com>
License: Apache 2.0
Project-URL: homepage, https://github.com/CUNY-CL/yoyodyne-pretrained
Keywords: computational linguistics,morphology,natural language processing,language
Classifier: Programming Language :: Python :: 3.10
Classifier: Programming Language :: Python :: 3.11
Classifier: Programming Language :: Python :: 3.12
Classifier: Programming Language :: Python :: 3.13
Classifier: Programming Language :: Python :: 3.14
Classifier: Development Status :: 4 - Beta
Classifier: Environment :: Console
Classifier: License :: OSI Approved :: Apache Software License
Classifier: Operating System :: OS Independent
Classifier: Topic :: Text Processing :: Linguistic
Requires-Python: <3.15,>=3.10
License-File: LICENSE.txt
Requires-Dist: PyYAML<7.0.0,>=6.0.2
Requires-Dist: jsonargparse[signatures]<5.0.0,>=4.40.0
Requires-Dist: lightning==2.6.0
Requires-Dist: omegaconf==2.3.0
Requires-Dist: torch==2.9.1
Requires-Dist: torchmetrics==1.8.2
Requires-Dist: transformers<5.0.0,>=4.44.0
Requires-Dist: yoyodyne>=0.4.9
Dynamic: license-file
